happywhale/__init__.py
happywhale/happywhale.py
happywhale-0.0.3.dist-info/LICENSE
happywhale-0.0.3.dist-info/METADATA
happywhale-0.0.3.dist-info/WHEEL
happywhale-0.0.3.dist-info/entry_points.txt
happywhale-0.0.3.dist-info/top_level.txt
happywhale-0.0.3.dist-info/RECORD
