Metadata-Version: 2.1
Name: happywhale
Version: 0.0.3
Summary: Simple CLI for HappyWhale.com
Home-page: https://github.com/samapriya/happywhale
Author: Samapriya Roy
Author-email: samapriya.roy@gmail.com
License: Apache 2.0
Classifier: Intended Audience :: Developers
Classifier: Intended Audience :: Science/Research
Classifier: Natural Language :: English
Classifier: License :: OSI Approved :: Apache Software License
Classifier: Programming Language :: Python :: 3.9
Classifier: Programming Language :: Python :: 3.10
Classifier: Operating System :: OS Independent
Classifier: Topic :: Scientific/Engineering :: Oceanography
License-File: LICENSE
Requires-Dist: requests >=2.31.0
Requires-Dist: pandas >=2.1.2
Requires-Dist: geojson >=2.5.0
Requires-Dist: geopandas >=0.9.0 ; platform_system != "Windows"
Requires-Dist: pipgeo >=0.0.6 ; platform_system == "Windows"
